uP.v
// Laboritorio 8 Ejercicio 01
module Contador12b(input wire  load,enable,clk,reset, input wire [11:0]valueLoad, output reg [11:0] out );

    always @ ( posedge clk, posedge reset, posedge load) begin
        if (load) out = valueLoad; //si load esta encendido deja pasar a la salida valueLoad
        else begin // en caso contrario, si reset esta en 1, en 0 se coloca la salida, en caso contrario
            if (reset) out = 0; // si enable es 1 el contador incrementa en 1 cada flanco
            else  if(enable == 1 ) out = out + 1;
        end 
    end
endmodule
//Laboratorio 8 Ejercicio 02 
module Memory(input wire [11:0] address, output wire [7:0] data );

    reg[7:0] memoria[4095:0]; // matriz d 4k 

    initial begin
        $readmemh("memory.list",memoria); // se lee la memoria
    end

    assign  data = memoria[address]; //a la salida data se asigna el valor en la fila address

endmodule

module  FlipFlopD1b(input d,enable,reset,clk,output reg q);

    always @(posedge clk, posedge reset) begin  //reset asincrono
        if (reset) q = 0; // si el reset esta activado la salida se coloca en 0
        else if (enable) q = d; //si reset esta en 0 y ademas esta enable en 1, entonces deja pasar d a q
    end

endmodule

module FlipFlopT(input enable, reset, clk, output wire q );
    
    FlipFlopD1b FF(~q,enable, reset,clk,q); // ya que lo que hace FF T es complementar la salida
    //se coloca ~q en la entrada del Flip Flop D, de forma que en cada flanco de subida, la salida Q
    // se complementa, siempre y cuando el enable este en 1, 

endmodule

//Lab 9 ejercicio 5
module Decode(input[6:0] address,output reg [12:0] value );

    always @(address) begin
    
        casez(address) //dependiendo del valor de address sale el decode. 

        7'b??????0 : value <= 13'b1000000001000;
        7'b00001?1 : value <= 13'b0100000001000;
        7'b00000?1 : value <= 13'b1000000001000;
        7'b00011?1 : value <= 13'b1000000001000;
        7'b00010?1 : value <= 13'b0100000001000;
        7'b0010??1 : value <= 13'b0001001000010;
        7'b0011??1 : value <= 13'b1001001100000;
        7'b0100??1 : value <= 13'b0011010000010;
        7'b0101??1 : value <= 13'b0011010000100;
        7'b0110??1 : value <= 13'b1011010100000;
        7'b0111??1 : value <= 13'b1000000111000;
        7'b1000?11 : value <= 13'b0100000001000;
        7'b1000?01 : value <= 13'b1000000001000;
        7'b1001?11 : value <= 13'b1000000001000;
        7'b1001?01 : value <= 13'b0100000001000;
        7'b1010??1 : value <= 13'b0011011000010;
        7'b1011??1 : value <= 13'b1011011100000;
        7'b1100??1 : value <= 13'b0100000001000;
        7'b1101??1 : value <= 13'b0000000001001;
        7'b1110??1 : value <= 13'b0011100000010;
        7'b1111??1 : value <= 13'b1011100100000;
        default : value <= 0; // si se ingresa cualquier otra direccion la salida es 0
        endcase
    end
endmodule

//Lab 9 ejercicio 04
module Triestate(input [3:0] in,input enable, output wire [3:0] y );
    // en general si el bit n de enable se encuentra en 0 el bit n de la salida se coloca 
    // en valor flotante, y en cambio si el bit n de enable esta en 1 deja pasar el valor
    // del bit n de in, a el bit n de y
    assign y[0] = (enable ? in[0] : 1'bz );
    assign y[1] = (enable ? in[1] : 1'bz );
    assign y[2] = (enable ? in[2] : 1'bz );
    assign y[3] = (enable ? in[3] : 1'bz );

endmodule

//Lab 10 ejercicio 
module FlipFlopD4b(input wire [3:0] D,input wire load, reset, clk, output reg[3:0] Q );

    always @(posedge clk, posedge reset) begin
        
        if (reset) Q = 0; //si esta en reset la salida es 0
        else if(load) begin //si load es 1 en el siguiente flanco de reloj deja pasar D a Q
            Q <= D;
        end
    end
endmodule

module FlipFlopD2b(input wire [1:0] D,input wire load, reset, clk, output reg[1:0] Q );

    always @(posedge clk, posedge reset) begin
        
        if (reset) Q = 0; //si esta en reset la salida es 0
        else if(load) begin //si load es 1 en el siguiente flanco de reloj deja pasar D a Q
            Q <= D;
        end
    end
endmodule

module RAM(input wire [11:0] address, input wire weRAM, csRAM, inout wire [3:0] data);
    reg [3:0] memoria[0:4095] ;//bloque de memoria de 4k posiciones
    reg [3:0] dataOut;

    assign data = ( (csRAM & ~weRAM) ? dataOut : 4'bzzzz);// cuando csRAM es 1 y weRAM es 0 se le asigna a la salida el valor de
                                                            //data out, en cualquier otro caso se coloca en alta impedancia

    always @ (weRAM or csRAM or data or address) begin  //siempbre que haya un cambio en estas variables se ejecuta 
        if(weRAM & csRAM)
            memoria[address] = data;
    
        else if (~weRAM & csRAM) dataOut = memoria[address];
        
    end
endmodule
// LAB 10 EJERCICIO 02
module ALU(input wire[3:0] A,B,input [2:0] control , output wire [3:0] out, output wire C, Z );
    reg[4:0] resultado; //registro en el cual se almacena el resultado
    assign Z = ~(resultado[0] | resultado[1] | resultado[2] | resultado[3]); 
    // siempre qque todos los bits de out sean 0 Z va a ser 1 en caso contrario sera 0
    assign out = resultado[4:0]; //la salida son los 4 bits menos significativos de resultado
    assign C = resultado[4] ;//C es el ultimo bit (el de acarreo) de la operacion

    always @ (A,B,control) begin  // siempre qeu cambie A, B o Control se ejecuta
        case(control)
            3'b000: resultado <= A; //deja pasar A
            3'b001: resultado <= A -B;  //resta a y B 
            3'b010: resultado <= B; // deja pasar B
            3'b011: resultado <= A + B; //suma a y b
            3'b100: resultado <= ~(A|B); // NOR A y B
            default: resultado <= 0; //si se ingresara cualquier otra combinacion
        endcase
    end
endmodule

module uP(input wire [3:0] pushbuttons, input reset, clock,
          output wire [11:0] PC, address_RAM, output wire [7:0] program_byte, output wire [3:0] instr, oprnd, data_bus, FF_out, accu,
          output wire phase, c_flag, z_flag);

    //-------------- SEÑAL ENTRANDE PARA EL DECODE---------------------------------
    wire [6:0] inDecode;
    assign inDecode = {instr,c_flag,z_flag,phase}; //el bus que va de entrada al decode, se concantenan buses mostrados
    wire [12:0] controlSignals; //bus de señales de ocntrol


    //----------------CONTROL DE FLUJO DEL PROGRAMA--------------------------------
    Decode decode(inDecode, controlSignals); // se conectan los buses necesarios para el modulo de decode
    //se conecta el bit loadPC con load, incPC con enable, las seniales de reloj y reset, y ademas la direccion de la ram
    Contador12b programCounter(controlSignals[11], controlSignals[12],clock,reset, address_RAM, PC );
    //la memoria de programa, se conecta pc a la direccion y program_byte a la salida
    Memory  ROM(PC, program_byte);
    //el modulo de fetch, en donde el load es controlado por el complenento del valor de phase.

    //------------------ BUS DE DATOS-----------------------------------------------------------
    FlipFlopD4b FetchOperand(program_byte[3:0], ~phase, reset, clock, oprnd);
    FlipFlopD4b FetchInstr(program_byte[7:4], ~phase, reset, clock, instr);
    //se concantenan oprnd y program_byte para generar el valor de address
    assign address_RAM = {oprnd,program_byte};
    //se genera la salida de phase
    FlipFlopT Phase(1'b1 ,reset, clock,phase);
    // se onceta oeoperand de controlSignal bus tri estado y la salida se conecta al bus de datos 
    Triestate   busDriverOprnad(oprnd,controlSignals[1],data_bus);
    //se conecta la memoria ram al bus de datos y se le conectan las señales de weRAM y csRAM ademas del bus de direcciones
    RAM ram(address_RAM,controlSignals[4],controlSignals[5],data_bus);
    //-----------------MODULO DE ALU Y EL ACUMULADOR -------------------------------------------
    wire [3:0] aluOut; //Salida de la alu
    wire c,z; //salidas c y z de la alu
    //se conecta el FF del acumilador a la senial de control respectiva y ademas su salida se conecta a la salida del modulo accu
    FlipFlopD4b acumulador(aluOut, controlSignals[10],reset, clock, accu);

    ALU unidadAritmetica(accu, data_bus,controlSignals[8:6],aluOut,c,z);
    // buffer tri estado que conecta la salida de la alu con el bus de datos
    Triestate aluOuput(aluOut,controlSignals[3],data_bus);
    // ff de banderas
    FlipFlopD2b banderas({c,z},controlSignals[9],reset, clock, {c_flag,z_flag});
    //---------------------------- PUERTOS DE SALIDA -------------------------------------------
    FlipFlopD4b salida(data_bus, controlSignals[0],reset,clock, FF_out);
    Triestate in(pushbutton, controlSignals[2],data_bus);

endmodule

uP_tb.v
module testbench();

    reg clk, res,enable,load;
    reg [11:0] carga;

    wire[11:0] out;

    Contador12b cont(load,enable,clk,res,carga,out);

    always  #1 clk <= ~clk;
    initial clk =0 ; //se inicializa el reloj

    initial begin
        res =0; enable = 0; load = 0; carga = 0;
        #1 res =1;
        #1 res = 0;
        #2 enable = 1;
        #50 res = 1;
        #2  res = 0;
        #10 carga = 255; 
        #4  load = 1;
        #10 load = 0;
        #10 enable = 0;
        #10 enable = 1;
        #10 res = 1;
        #2  res = 0;
        #10 carga = 4090;
        #1  load = 1;
        #4  load = 0;
        #4  enable = 0;
        #2  enable = 1;
        #35 $finish;
    end

    initial begin
        $dumpfile("uP_tb.vcd");
        $dumpvars(0,testbench);
    end


endmodule

uP_tb.vcd
$date
	Mon Nov 16 17:32:20 2020
$end
$version
	Icarus Verilog
$end
$timescale
	1ps
$end
$scope module testbench $end
$var wire 12 ! out [11:0] $end
$var reg 12 " carga [11:0] $end
$var reg 1 # clk $end
$var reg 1 $ enable $end
$var reg 1 % load $end
$var reg 1 & res $end
$scope module cont $end
$var wire 1 # clk $end
$var wire 1 $ enable $end
$var wire 1 % load $end
$var wire 1 & reset $end
$var wire 12 ' valueLoad [11:0] $end
$var reg 12 ( out [11:0] $end
$upscope $end
$upscope $end
$enddefinitions $end
#0
$dumpvars
bx (
b0 '
0&
0%
0$
0#
b0 "
bx !
$end
#1
1#
b0 !
b0 (
1&
#2
0#
0&
#3
1#
#4
0#
1$
#5
b1 !
b1 (
1#
#6
0#
#7
b10 !
b10 (
1#
#8
0#
#9
b11 !
b11 (
1#
#10
0#
#11
b100 !
b100 (
1#
#12
0#
#13
b101 !
b101 (
1#
#14
0#
#15
b110 !
b110 (
1#
#16
0#
#17
b111 !
b111 (
1#
#18
0#
#19
b1000 !
b1000 (
1#
#20
0#
#21
b1001 !
b1001 (
1#
#22
0#
#23
b1010 !
b1010 (
1#
#24
0#
#25
b1011 !
b1011 (
1#
#26
0#
#27
b1100 !
b1100 (
1#
#28
0#
#29
b1101 !
b1101 (
1#
#30
0#
#31
b1110 !
b1110 (
1#
#32
0#
#33
b1111 !
b1111 (
1#
#34
0#
#35
b10000 !
b10000 (
1#
#36
0#
#37
b10001 !
b10001 (
1#
#38
0#
#39
b10010 !
b10010 (
1#
#40
0#
#41
b10011 !
b10011 (
1#
#42
0#
#43
b10100 !
b10100 (
1#
#44
0#
#45
b10101 !
b10101 (
1#
#46
0#
#47
b10110 !
b10110 (
1#
#48
0#
#49
b10111 !
b10111 (
1#
#50
0#
#51
b11000 !
b11000 (
1#
#52
0#
#53
b11001 !
b11001 (
1#
#54
0#
b0 !
b0 (
1&
#55
1#
#56
0#
0&
#57
b1 !
b1 (
1#
#58
0#
#59
b10 !
b10 (
1#
#60
0#
#61
b11 !
b11 (
1#
#62
0#
#63
b100 !
b100 (
1#
#64
0#
#65
b101 !
b101 (
1#
#66
0#
b11111111 "
b11111111 '
#67
b110 !
b110 (
1#
#68
0#
#69
b111 !
b111 (
1#
#70
0#
b11111111 !
b11111111 (
1%
#71
1#
#72
0#
#73
1#
#74
0#
#75
1#
#76
0#
#77
1#
#78
0#
#79
1#
#80
0#
0%
#81
b100000000 !
b100000000 (
1#
#82
0#
#83
b100000001 !
b100000001 (
1#
#84
0#
#85
b100000010 !
b100000010 (
1#
#86
0#
#87
b100000011 !
b100000011 (
1#
#88
0#
#89
b100000100 !
b100000100 (
1#
#90
0#
0$
#91
1#
#92
0#
#93
1#
#94
0#
#95
1#
#96
0#
#97
1#
#98
0#
#99
1#
#100
0#
1$
#101
b100000101 !
b100000101 (
1#
#102
0#
#103
b100000110 !
b100000110 (
1#
#104
0#
#105
b100000111 !
b100000111 (
1#
#106
0#
#107
b100001000 !
b100001000 (
1#
#108
0#
#109
b100001001 !
b100001001 (
1#
#110
0#
b0 !
b0 (
1&
#111
1#
#112
0#
0&
#113
b1 !
b1 (
1#
#114
0#
#115
b10 !
b10 (
1#
#116
0#
#117
b11 !
b11 (
1#
#118
0#
#119
b100 !
b100 (
1#
#120
0#
#121
b101 !
b101 (
1#
#122
0#
b111111111010 "
b111111111010 '
#123
1#
b111111111010 !
b111111111010 (
1%
#124
0#
#125
1#
#126
0#
#127
b111111111011 !
b111111111011 (
1#
0%
#128
0#
#129
b111111111100 !
b111111111100 (
1#
#130
0#
#131
1#
0$
#132
0#
#133
b111111111101 !
b111111111101 (
1#
1$
#134
0#
#135
b111111111110 !
b111111111110 (
1#
#136
0#
#137
b111111111111 !
b111111111111 (
1#
#138
0#
#139
b0 !
b0 (
1#
#140
0#
#141
b1 !
b1 (
1#
#142
0#
#143
b10 !
b10 (
1#
#144
0#
#145
b11 !
b11 (
1#
#146
0#
#147
b100 !
b100 (
1#
#148
0#
#149
b101 !
b101 (
1#
#150
0#
#151
b110 !
b110 (
1#
#152
0#
#153
b111 !
b111 (
1#
#154
0#
#155
b1000 !
b1000 (
1#
#156
0#
#157
b1001 !
b1001 (
1#
#158
0#
#159
b1010 !
b1010 (
1#
#160
0#
#161
b1011 !
b1011 (
1#
#162
0#
#163
b1100 !
b1100 (
1#
#164
0#
#165
b1101 !
b1101 (
1#
#166
0#
#167
b1110 !
b1110 (
1#
