modulos.v
// en este documento se encuentran todos los modulos que se usaran en el microprocesador
// ------------------ CONTADORES ---------------------------------------------------------------

module Contador12b(input wire  load,enable,clk,reset, input wire [11:0]valueLoad, output reg [11:0] out );

    always @ (posedge clk, posedge reset) begin
        if (load) out <= valueLoad;// de lo contrario se revisa reset si es un entonces la salida es 0
        else if (reset) out <= 0;//de lo contrario se revisa enable y si es 1 la salida se le aumenta 1
        else if(enable) out <= out + 1;// si es 1 entonces se asigna el valor cargado a la salida
            else out <= out;
    end
endmodule

//------------ AQUI VAN LOS FLIP FLOPS ----------------------------------------------------------
module  FlipFlopD1b(input d,enable,reset,clk,output reg q);

    always @(posedge clk, posedge reset) begin  //reset asincrono
        if (reset) q = 0; // si el reset esta activado la salida se coloca en 0
        else if (enable) q = d; //si reset esta en 0 y ademas esta enable en 1, entonces deja pasar d a q
    end

endmodule

module FlipFlopD2b(input wire [1:0] d, input wire enable, reset, clk, output reg [1:0] q );

    always @(posedge clk, posedge reset) begin  //reset asincrono
        if (reset) q = 0; // si el reset esta activado la salida se coloca en 0
        else if (enable) q = d; //si reset esta en 0 y ademas esta enable en 1, entonces deja pasar d a q
    end

endmodule

module FlipFlopD4b(input [3:0] d, input wire enable, reset, clk, output reg [3:0] q );

    always @(posedge clk, posedge reset) begin  //reset asincrono
        if (reset) q = 0; // si el reset esta activado la salida se coloca en 0
        else if (enable) q = d; //si reset esta en 0 y ademas esta enable en 1, entonces deja pasar d a q
    end
endmodule

//Lab 9 Ejercicio 2
module FlipFlopT(input enable, reset, clk, output wire q );
    
    FlipFlopD1b FF(~q,enable, reset,clk,q); // ya que lo que hace FF T es complementar la salida
    //se coloca ~q en la entrada del Flip Flop D, de forma que en cada flanco de subida, la salida Q
    // se complementa, siempre y cuando el enable este en 1, 

endmodule

//---------------- MEMORIAS  --------------------------------------
module Memory(input wire [11:0] address, output wire [7:0] data );

    reg[7:0] memoria[4095:0];

    initial begin
        $readmemh("testbench.list",memoria); // se lee la memoria
    end

    assign  data = memoria[address];

endmodule

module RAM(input [11:0] address, input cs, input we, inout[3:0] data );
    reg [3:0] dataOut;
    reg [3:0] ram[4095:0];

    assign data = (cs & ~we) ? dataOut : 4'bzzzz; // si cs es 1 y we es 0 se le asigna el valor de dataOut de lo contradio esta en z

    always @(address, cs, we, data) begin
        if(cs & ~we) dataOut = ram[address]; //si esta seleccionado pero no habilitado para escritura coloca enla salida lo de la direccion
        else if(cs & we) ram[address] = data;
    end

endmodule

module Decode(input[6:0] address,output reg [12:0] value );

    always @(address) begin
        
        casez(address)

        7'b??????0 : value = 13'b1000000001000;
        7'b00001?1 : value = 13'b0100000001000;
        7'b00000?1 : value = 13'b1000000001000;
        7'b00011?1 : value = 13'b1000000001000;
        7'b00010?1 : value = 13'b0100000001000;
        7'b0010??1 : value = 13'b0001001000010;
        7'b0011??1 : value = 13'b1001001100000;
        7'b0100??1 : value = 13'b0011010000010;
        7'b0101??1 : value = 13'b0011010000100;
        7'b0110??1 : value = 13'b1011010100000;
        7'b0111??1 : value = 13'b1000000111000;
        7'b1000?11 : value = 13'b0100000001000;
        7'b1000?01 : value = 13'b1000000001000;
        7'b1001?11 : value = 13'b1000000001000;
        7'b1001?01 : value = 13'b0100000001000;
        7'b1010??1 : value = 13'b0011011000010;
        7'b1011??1 : value = 13'b1011011100000;
        7'b1100??1 : value = 13'b0100000001000;
        7'b1101??1 : value = 13'b0000000001001;
        7'b1110??1 : value = 13'b0011100000010;
        7'b1111??1 : value = 13'b1011100100000;
        default : value = 0; // si se ingresa cualquier otra direccion la salida es 0

        endcase


    end


endmodule
//--------------- OTROS MODULOS ----------------------------------
module Triestate(input [3:0] in, input enable, output wire [3:0] y );
    // en general si  enable se encuentra en 0  la salida se coloca 
    // en valor flotante, y en cambio si el bit de enable esta en 1 deja pasar el valor
    // del bit in, a ey
    assign y[0] = (enable? in[0] : 1'bz );
    assign y[1] = (enable? in[1] : 1'bz );
    assign y[2] = (enable? in[2] : 1'bz );
    assign y[3] = (enable? in[3] : 1'bz );

endmodule

module ALU(input wire[3:0] A,B,input [2:0] control , output wire [3:0] out, output wire C, Z );
    reg[4:0] resultado; //registro en el cual se almacena el resultado
    assign Z = ~(resultado[0] | resultado[1] | resultado[2] | resultado[3]); 
    // siempre qque todos los bits de out sean 0 Z va a ser 1 en caso contrario sera 0
    assign out = resultado[3:0]; //la salida son los 4 bits menos significativos de resultado
    assign C = resultado[4] ;//C es el ultimo bit (el de acarreo) de la operacion

    always @ (A,B,control) begin  // siempre qeu cambie A, B o Control se ejecuta
        case(control)
            3'b000: resultado <= A; //deja pasar A
            3'b001: resultado <= A - B;  //resta a y B 
            3'b010: resultado <= B; // deja pasar B
            3'b011: resultado <= A + B; //suma a y b
            3'b100: resultado <= {1'b0, ~(A  & B)} ; // NAND A y B
            default: resultado <= 0; //si se ingresara cualquier otra combinacion
        endcase
    end
endmodule

uP.v
module uP(input  clock, reset, input [3:0] pushbuttons, output [11:0] PC, address_RAM, output [7:0] program_byte,
          output [3:0] instr, oprnd, data_bus, FF_out, accu, output phase, c_flag, z_flag);
   
    
    // estos con cables que son usados para conectar las salidas de decode
    wire loadPC;
    wire incPC;
    wire loadA;
    wire loadFlags;
    wire [2:0] opALU;
    wire cs;
    wire we;
    wire oeALU;
    wire oeIn;
    wire oeOprnd;
    wire loadOut;
    wire [12:0] outDecode;
    wire [6:0] inDecode;


    assign inDecode = {instr, c_flag,z_flag,phase}; 
    Decode dec(inDecode, outDecode);
    //se asignaa cada cable el valor de la salida del decode
    assign incPC = outDecode[12];
    assign loadPC = outDecode[11];
    assign loadA = outDecode[10];
    assign loadFlags = outDecode[9];
    assign opALU = outDecode[8:6];
    assign cs = outDecode[5];
    assign we = outDecode[4];
    assign oeALU = outDecode[3];
    assign oeIn = outDecode [2];
    assign oeOprnd = outDecode [1];
    assign loadOut = outDecode[0];

    assign address_RAM = {oprnd,program_byte};
    //------------------ CONTROL DEL PROGRAMA -------------------------------
    Contador12b programCouter(loadPC,incPC, clock, reset, address_RAM, PC ); //program counter
    Memory  programROM(PC, program_byte); // memoria de programa
    FlipFlopD4b fetchOp(program_byte[3:0], ~phase, reset, clock, oprnd);
    FlipFlopD4b  fetchIns(program_byte[7:4], ~phase, reset, clock, instr);
    FlipFlopT   fase(1'b1, reset, clock, phase);
    //-----------------------------------------------------------------------
    //------------------- MANEJO DE DATOS------------------------------------
    wire[3:0] outAlu;
    wire c,z;
    Triestate bufferOprnd(oprnd,oeOprnd,data_bus);
    Triestate bufferIn(pushbuttons,oeIn,data_bus);
    Triestate bufferAlu(outAlu,oeALU, data_bus);

    RAM ram(address_RAM,cs,we,data_bus);
    //------------------- ALU ----------------------------------------------
    FlipFlopD4b accumulador(outAlu, loadA,reset, clock, accu );
    ALU unidadAritmetica(accu,data_bus, opALU, outAlu,c , z);

    FlipFlopD1b flagsC(c,loadFlags,reset, clock, c_flag);
    FlipFlopD1b flagsZ(z,loadFlags,reset, clock, z_flag);
    //--------------- Salida -----------------------------------------------
    FlipFlopD4b salida(data_bus,loadOut, reset, clock, FF_out );
    
    

endmodule

uP_tb.v
module testbenchMio();

    reg clock, reset;
    reg [3:0] pushbuttons;
    wire phase, c_flag, z_flag;
    wire [3:0] instr, oprnd, accu, data_bus, FF_out;
    wire [7:0] program_byte;
    wire [11:0] PC, address_RAM;

    uP uPmodule(.clock(clock),
                .reset(reset),
                .pushbuttons(pushbuttons),
                .phase(phase),
                .c_flag(c_flag),
                .z_flag(z_flag),
                .instr(instr),
                .oprnd(oprnd),
                .accu(accu),
                .data_bus(data_bus),
                .FF_out(FF_out),    
                .program_byte(program_byte),
                .PC(PC),
                .address_RAM(address_RAM));

    initial
        #1000 $finish;

    always
        #5 clock = ~clock;

    initial begin
        #1  reset = 1;clock=0;
        #1  reset = 0; pushbuttons = 10;
        #100 $display("el valor en la salida es: %h",FF_out);
    end

    initial begin
        $dumpfile("uP_tb.vcd");
        $dumpvars(0,testbenchMio);
    end

endmodule

uP_tb.vcd
$date
	Sat Nov 21 16:15:56 2020
$end
$version
	Icarus Verilog
$end
$timescale
	1ps
$end
$scope module testbenchMio $end
$var wire 4 ! data_bus [3:0] $end
$var wire 1 " z_flag $end
$var wire 8 # program_byte [7:0] $end
$var wire 1 $ phase $end
$var wire 4 % oprnd [3:0] $end
$var wire 4 & instr [3:0] $end
$var wire 1 ' c_flag $end
$var wire 12 ( address_RAM [11:0] $end
$var wire 4 ) accu [3:0] $end
$var wire 12 * PC [11:0] $end
$var wire 4 + FF_out [3:0] $end
$var reg 1 , clock $end
$var reg 4 - pushbuttons [3:0] $end
$var reg 1 . reset $end
$scope module uPmodule $end
$var wire 1 , clock $end
$var wire 4 / data_bus [3:0] $end
$var wire 4 0 pushbuttons [3:0] $end
$var wire 1 . reset $end
$var wire 1 " z_flag $end
$var wire 1 1 z $end
$var wire 1 2 we $end
$var wire 8 3 program_byte [7:0] $end
$var wire 1 $ phase $end
$var wire 13 4 outDecode [12:0] $end
$var wire 4 5 outAlu [3:0] $end
$var wire 4 6 oprnd [3:0] $end
$var wire 3 7 opALU [2:0] $end
$var wire 1 8 oeOprnd $end
$var wire 1 9 oeIn $end
$var wire 1 : oeALU $end
$var wire 1 ; loadPC $end
$var wire 1 < loadOut $end
$var wire 1 = loadFlags $end
$var wire 1 > loadA $end
$var wire 4 ? instr [3:0] $end
$var wire 1 @ incPC $end
$var wire 7 A inDecode [6:0] $end
$var wire 1 B cs $end
$var wire 1 ' c_flag $end
$var wire 1 C c $end
$var wire 12 D address_RAM [11:0] $end
$var wire 4 E accu [3:0] $end
$var wire 12 F PC [11:0] $end
$var wire 4 G FF_out [3:0] $end
$scope module accumulador $end
$var wire 1 , clk $end
$var wire 1 > enable $end
$var wire 1 . reset $end
$var wire 4 H d [3:0] $end
$var reg 4 I q [3:0] $end
$upscope $end
$scope module bufferAlu $end
$var wire 1 : enable $end
$var wire 4 J y [3:0] $end
$var wire 4 K in [3:0] $end
$upscope $end
$scope module bufferIn $end
$var wire 1 9 enable $end
$var wire 4 L in [3:0] $end
$var wire 4 M y [3:0] $end
$upscope $end
$scope module bufferOprnd $end
$var wire 1 8 enable $end
$var wire 4 N y [3:0] $end
$var wire 4 O in [3:0] $end
$upscope $end
$scope module dec $end
$var wire 7 P address [6:0] $end
$var reg 13 Q value [12:0] $end
$upscope $end
$scope module fase $end
$var wire 1 , clk $end
$var wire 1 R enable $end
$var wire 1 . reset $end
$var wire 1 $ q $end
$scope module FF $end
$var wire 1 , clk $end
$var wire 1 S d $end
$var wire 1 R enable $end
$var wire 1 . reset $end
$var reg 1 $ q $end
$upscope $end
$upscope $end
$scope module fetchIns $end
$var wire 1 , clk $end
$var wire 4 T d [3:0] $end
$var wire 1 U enable $end
$var wire 1 . reset $end
$var reg 4 V q [3:0] $end
$upscope $end
$scope module fetchOp $end
$var wire 1 , clk $end
$var wire 4 W d [3:0] $end
$var wire 1 X enable $end
$var wire 1 . reset $end
$var reg 4 Y q [3:0] $end
$upscope $end
$scope module flagsC $end
$var wire 1 , clk $end
$var wire 1 = enable $end
$var wire 1 . reset $end
$var wire 1 C d $end
$var reg 1 ' q $end
$upscope $end
$scope module flagsZ $end
$var wire 1 , clk $end
$var wire 1 = enable $end
$var wire 1 . reset $end
$var wire 1 1 d $end
$var reg 1 " q $end
$upscope $end
$scope module programCouter $end
$var wire 1 , clk $end
$var wire 1 @ enable $end
$var wire 1 ; load $end
$var wire 1 . reset $end
$var wire 12 Z valueLoad [11:0] $end
$var reg 12 [ out [11:0] $end
$upscope $end
$scope module programROM $end
$var wire 12 \ address [11:0] $end
$var wire 8 ] data [7:0] $end
$upscope $end
$scope module ram $end
$var wire 12 ^ address [11:0] $end
$var wire 1 B cs $end
$var wire 4 _ data [3:0] $end
$var wire 1 2 we $end
$var reg 4 ` dataOut [3:0] $end
$upscope $end
$scope module salida $end
$var wire 1 , clk $end
$var wire 4 a d [3:0] $end
$var wire 1 < enable $end
$var wire 1 . reset $end
$var reg 4 b q [3:0] $end
$upscope $end
$scope module unidadAritmetica $end
$var wire 4 c A [3:0] $end
$var wire 4 d B [3:0] $end
$var wire 1 1 Z $end
$var wire 3 e control [2:0] $end
$var wire 4 f out [3:0] $end
$var wire 1 C C $end
$var reg 5 g resultado [4:0] $end
$upscope $end
$upscope $end
$upscope $end
$enddefinitions $end
#0
$dumpvars
bx g
bx f
bx e
bx d
bx c
bx b
bx a
bx `
bx _
bx ^
bx ]
bx \
bx [
bx Z
bx Y
xX
bx W
bx V
xU
bx T
xS
1R
bx Q
bx P
bx O
bx N
bx M
bx L
bx K
bx J
bx I
bx H
bx G
bx F
bx E
bx D
xC
xB
bx A
x@
bx ?
x>
x=
x<
x;
x:
x9
x8
bx 7
bx 6
bx 5
bx 4
bx 3
x2
x1
bx 0
bx /
x.
bx -
x,
bx +
bx *
bx )
bx (
x'
bx &
bx %
x$
bx #
x"
bx !
$end
#1
11
b0 !
b0 /
b0 J
b0 M
b0 N
b0 _
b0 a
b0 d
b0 5
b0 H
b0 K
b0 f
0C
b100 T
b100 W
b0 g
b1000100 #
b1000100 3
b1000100 ]
b0 *
b0 F
b0 [
b0 \
0<
08
09
1:
02
0B
b0 7
b0 e
0=
0>
0;
1@
1S
1U
1X
b1000000001000 4
b1000000001000 Q
b1000100 (
b1000100 D
b1000100 Z
b1000100 ^
b0 %
b0 6
b0 O
b0 Y
b0 &
b0 ?
b0 V
0$
b0 )
b0 E
b0 I
b0 c
0'
b0 A
b0 P
0"
b0 +
b0 G
b0 b
0,
1.
#2
b1010 -
b1010 0
b1010 L
0.
#5
01
b100 5
b100 H
b100 K
b100 f
b111 T
b0 W
b100 g
b1110000 #
b1110000 3
b1110000 ]
b1 *
b1 F
b1 [
b1 \
b100 !
b100 /
b100 J
b100 M
b100 N
b100 _
b100 a
b100 d
18
0:
b10 7
b10 e
1=
1>
0@
0S
0U
0X
b11010000010 4
b11010000010 Q
1$
b100001 A
b100001 P
b100 &
b100 ?
b100 V
b10001110000 (
b10001110000 D
b10001110000 Z
b10001110000 ^
b100 %
b100 6
b100 O
b100 Y
1,
#10
0,
#15
08
1:
b0 7
b0 e
0=
0>
1@
1S
b1000000001000 4
b1000000001000 Q
1U
1X
b100000 A
b100000 P
0$
b100 )
b100 E
b100 I
b100 c
1,
#20
0,
#25
b0 T
b0 #
b0 3
b0 ]
b10 *
b10 F
b10 [
b10 \
b100 !
b100 /
b100 J
b100 M
b100 N
b100 _
b100 a
b100 d
12
1B
0S
0U
0X
b1000000111000 4
b1000000111000 Q
1$
b111001 A
b111001 P
b111 &
b111 ?
b111 V
b0 (
b0 D
b0 Z
b0 ^
b0 %
b0 6
b0 O
b0 Y
1,
#30
0,
#35
b100 T
b1001 W
b1001001 (
b1001001 D
b1001001 Z
b1001001 ^
b1001001 #
b1001001 3
b1001001 ]
b11 *
b11 F
b11 [
b11 \
02
0B
1S
b1000000001000 4
b1000000001000 Q
1U
1X
b111000 A
b111000 P
0$
1,
#40
0,
#45
b1001 5
b1001 H
b1001 K
b1001 f
b1011 T
b0 W
b1001 g
b10110000 #
b10110000 3
b10110000 ]
b100 *
b100 F
b100 [
b100 \
b1001 !
b1001 /
b1001 J
b1001 M
b1001 N
b1001 _
b1001 a
b1001 d
18
0:
b10 7
b10 e
1=
1>
0@
0S
0U
0X
b11010000010 4
b11010000010 Q
1$
b100001 A
b100001 P
b100 &
b100 ?
b100 V
b100110110000 (
b100110110000 D
b100110110000 Z
b100110110000 ^
b1001 %
b1001 6
b1001 O
b1001 Y
1,
#50
0,
#55
08
1:
b0 7
b0 e
0=
0>
1@
1S
b1000000001000 4
b1000000001000 Q
1U
1X
b100000 A
b100000 P
0$
b1001 )
b1001 E
b1001 I
b1001 c
1,
#60
0,
#65
01
b1101 5
b1101 H
b1101 K
b1101 f
0C
b0 T
b100 `
b1101 g
b0 #
b0 3
b0 ]
b101 *
b101 F
b101 [
b101 \
b100 !
b100 /
b100 J
b100 M
b100 N
b100 _
b100 a
b100 d
0:
1B
b11 7
b11 e
1=
1>
0S
0U
0X
b1011011100000 4
b1011011100000 Q
1$
b1011001 A
b1011001 P
b1011 &
b1011 ?
b1011 V
b0 (
b0 D
b0 Z
b0 ^
b0 %
b0 6
b0 O
b0 Y
1,
#70
0,
#75
b1101 T
b1 W
b1101 g
b11010001 (
b11010001 D
b11010001 Z
b11010001 ^
b11010001 #
b11010001 3
b11010001 ]
b110 *
b110 F
b110 [
b110 \
b1101 !
b1101 /
b1101 J
b1101 M
b1101 N
b1101 _
b1101 a
b1101 d
1:
0B
b0 7
b0 e
0=
0>
1S
b1000000001000 4
b1000000001000 Q
1U
1X
b1011000 A
b1011000 P
0$
b1101 )
b1101 E
b1101 I
b1101 c
1,
#80
0,
#85
b101 T
b11 W
b1010011 #
b1010011 3
b1010011 ]
b111 *
b111 F
b111 [
b111 \
1<
0@
0S
0U
0X
b1001 4
b1001 Q
1$
b1101001 A
b1101001 P
b1101 &
b1101 ?
b1101 V
b101010011 (
b101010011 D
b101010011 Z
b101010011 ^
b1 %
b1 6
b1 O
b1 Y
1,
#90
0,
#95
0<
1@
1S
b1000000001000 4
b1000000001000 Q
1U
1X
b1101000 A
b1101000 P
0$
b1101 +
b1101 G
b1101 b
1,
#100
0,
#105
b1010 5
b1010 H
b1010 K
b1010 f
b1010 T
b101 W
b1010 g
b10100101 #
b10100101 3
b10100101 ]
b1000 *
b1000 F
b1000 [
b1000 \
b1010 !
b1010 /
b1010 J
b1010 M
b1010 N
b1010 _
b1010 a
b1010 d
19
0:
b10 7
b10 e
1=
1>
0@
0S
0U
0X
b11010000100 4
b11010000100 Q
1$
b101001 A
b101001 P
b101 &
b101 ?
b101 V
b1110100101 (
b1110100101 D
b1110100101 Z
b1110100101 ^
b11 %
b11 6
b11 O
b11 Y
1,
#110
0,
#115
09
1:
b0 7
b0 e
0=
0>
1@
1S
b1000000001000 4
b1000000001000 Q
1U
1X
b101000 A
b101000 P
0$
b1010 )
b1010 E
b1010 I
b1010 c
1,
#120
0,
#125
b1111 5
b1111 H
b1111 K
b1111 f
b1101 T
b1 W
b1111 g
b11010001 #
b11010001 3
b11010001 ]
b1001 *
b1001 F
b1001 [
b1001 \
b101 !
b101 /
b101 J
b101 M
b101 N
b101 _
b101 a
b101 d
18
0:
b11 7
b11 e
1=
1>
0@
0S
0U
0X
b11011000010 4
b11011000010 Q
1$
b1010001 A
b1010001 P
b1010 &
b1010 ?
b1010 V
b10111010001 (
b10111010001 D
b10111010001 Z
b10111010001 ^
b101 %
b101 6
b101 O
b101 Y
1,
#130
0,
#135
b1111 g
b1111 !
b1111 /
b1111 J
b1111 M
b1111 N
b1111 _
b1111 a
b1111 d
08
1:
b0 7
b0 e
0=
0>
1@
1S
b1000000001000 4
b1000000001000 Q
1U
1X
b1010000 A
b1010000 P
0$
b1111 )
b1111 E
b1111 I
b1111 c
1,
#140
0,
#145
b111 T
b0 W
b1110000 #
b1110000 3
b1110000 ]
b1010 *
b1010 F
b1010 [
b1010 \
1<
0@
0S
0U
0X
b1001 4
b1001 Q
1$
b1101001 A
b1101001 P
b1101 &
b1101 ?
b1101 V
b101110000 (
b101110000 D
b101110000 Z
b101110000 ^
b1 %
b1 6
b1 O
b1 Y
1,
#150
0,
#155
0<
1@
1S
b1000000001000 4
b1000000001000 Q
1U
1X
b1101000 A
b1101000 P
0$
b1111 +
b1111 G
b1111 b
1,
#160
0,
#165
b0 T
b1 W
b1 #
b1 3
b1 ]
b1011 *
b1011 F
b1011 [
b1011 \
b1111 !
b1111 /
b1111 J
b1111 M
b1111 N
b1111 _
b1111 a
b1111 d
12
1B
0S
0U
0X
b1000000111000 4
b1000000111000 Q
1$
b111001 A
b111001 P
b111 &
b111 ?
b111 V
b1 (
b1 D
b1 Z
b1 ^
b0 %
b0 6
b0 O
b0 Y
1,
#170
0,
#175
b100 T
b0 W
b1000000 (
b1000000 D
b1000000 Z
b1000000 ^
b1000000 #
b1000000 3
b1000000 ]
b1100 *
b1100 F
b1100 [
b1100 \
02
0B
1S
b1000000001000 4
b1000000001000 Q
1U
1X
b111000 A
b111000 P
0$
1,
#180
0,
#185
11
b0 5
b0 H
b0 K
b0 f
b1110 T
b1111 W
b0 g
b11101111 (
b11101111 D
b11101111 Z
b11101111 ^
b11101111 #
b11101111 3
b11101111 ]
b1101 *
b1101 F
b1101 [
b1101 \
b0 !
b0 /
b0 J
b0 M
b0 N
b0 _
b0 a
b0 d
18
0:
b10 7
b10 e
1=
1>
0@
0S
0U
0X
b11010000010 4
b11010000010 Q
1$
b100001 A
b100001 P
b100 &
b100 ?
b100 V
1,
#190
0,
#195
08
1:
b0 7
b0 e
0=
0>
1@
1S
1U
1X
b1000000001000 4
b1000000001000 Q
0$
b0 )
b0 E
b0 I
b0 c
b100010 A
b100010 P
1"
1,
#200
0,
#205
01
b1111 5
b1111 H
b1111 K
b1111 f
b111 T
b0 W
b1111 g
b1110000 #
b1110000 3
b1110000 ]
b1110 *
b1110 F
b1110 [
b1110 \
b1111 !
b1111 /
b1111 J
b1111 M
b1111 N
b1111 _
b1111 a
b1111 d
18
0:
b100 7
b100 e
1=
1>
0@
0S
0U
0X
b11100000010 4
b11100000010 Q
1$
b1110011 A
b1110011 P
b1110 &
b1110 ?
b1110 V
b111101110000 (
b111101110000 D
b111101110000 Z
b111101110000 ^
b1111 %
b1111 6
b1111 O
b1111 Y
1,
#210
0,
#215
b1111 g
08
1:
b0 7
b0 e
0=
0>
1@
1S
1U
1X
b1000000001000 4
b1000000001000 Q
0$
b1111 )
b1111 E
b1111 I
b1111 c
b1110000 A
b1110000 P
0"
1,
#220
0,
#225
b0 T
b0 #
b0 3
b0 ]
b1111 *
b1111 F
b1111 [
b1111 \
b1111 !
b1111 /
b1111 J
b1111 M
b1111 N
b1111 _
b1111 a
b1111 d
12
1B
0S
0U
0X
b1000000111000 4
b1000000111000 Q
1$
b111001 A
b111001 P
b111 &
b111 ?
b111 V
b0 (
b0 D
b0 Z
b0 ^
b0 %
b0 6
b0 O
b0 Y
1,
#230
0,
#235
b100 T
b1111 W
b1001111 (
b1001111 D
b1001111 Z
b1001111 ^
b1001111 #
b1001111 3
b1001111 ]
b10000 *
b10000 F
b10000 [
b10000 \
02
0B
1S
b1000000001000 4
b1000000001000 Q
1U
1X
b111000 A
b111000 P
0$
1,
#240
0,
#245
b1111 T
b0 W
b11110000 #
b11110000 3
b11110000 ]
b10001 *
b10001 F
b10001 [
b10001 \
b1111 !
b1111 /
b1111 J
b1111 M
b1111 N
b1111 _
b1111 a
b1111 d
18
0:
b10 7
b10 e
1=
1>
0@
0S
0U
0X
b11010000010 4
b11010000010 Q
1$
b100001 A
b100001 P
b100 &
b100 ?
b100 V
b111111110000 (
b111111110000 D
b111111110000 Z
b111111110000 ^
b1111 %
b1111 6
b1111 O
b1111 Y
1,
#250
0,
#255
08
1:
b0 7
b0 e
0=
0>
1@
1S
b1000000001000 4
b1000000001000 Q
1U
1X
b100000 A
b100000 P
0$
1,
#260
0,
#265
11
b0 5
b0 H
b0 K
b0 f
b0 T
b0 g
b0 #
b0 3
b0 ]
b10010 *
b10010 F
b10010 [
b10010 \
b1111 !
b1111 /
b1111 J
b1111 M
b1111 N
b1111 _
b1111 a
b1111 d
b1111 `
0:
1B
b100 7
b100 e
1=
1>
0S
0U
0X
b1011100100000 4
b1011100100000 Q
1$
b1111001 A
b1111001 P
b1111 &
b1111 ?
b1111 V
b0 (
b0 D
b0 Z
b0 ^
b0 %
b0 6
b0 O
b0 Y
1,
#270
0,
#275
b1101 T
b0 g
b11010000 (
b11010000 D
b11010000 Z
b11010000 ^
b11010000 #
b11010000 3
b11010000 ]
b10011 *
b10011 F
b10011 [
b10011 \
b0 !
b0 /
b0 J
b0 M
b0 N
b0 _
b0 a
b0 d
1:
0B
b0 7
b0 e
0=
0>
1S
1U
1X
b1000000001000 4
b1000000001000 Q
0$
b0 )
b0 E
b0 I
b0 c
b1111010 A
b1111010 P
1"
1,
#280
0,
#285
b100 T
b100 W
b1000100 (
b1000100 D
b1000100 Z
b1000100 ^
b1000100 #
b1000100 3
b1000100 ]
b10100 *
b10100 F
b10100 [
b10100 \
1<
0@
0S
0U
0X
b1001 4
b1001 Q
1$
b1101011 A
b1101011 P
b1101 &
b1101 ?
b1101 V
1,
#290
0,
#295
0<
1@
1S
b1000000001000 4
b1000000001000 Q
1U
1X
b1101010 A
b1101010 P
0$
b0 +
b0 G
b0 b
1,
#300
0,
#305
01
b100 5
b100 H
b100 K
b100 f
b1100 T
b0 W
b100 g
b11000000 #
b11000000 3
b11000000 ]
b10101 *
b10101 F
b10101 [
b10101 \
b100 !
b100 /
b100 J
b100 M
b100 N
b100 _
b100 a
b100 d
18
0:
b10 7
b10 e
1=
1>
0@
0S
0U
0X
b11010000010 4
b11010000010 Q
1$
b100011 A
b100011 P
b100 &
b100 ?
b100 V
b10011000000 (
b10011000000 D
b10011000000 Z
b10011000000 ^
b100 %
b100 6
b100 O
b100 Y
1,
#310
0,
#315
08
1:
b0 7
b0 e
0=
0>
1@
1S
1U
1X
b1000000001000 4
b1000000001000 Q
0$
b100 )
b100 E
b100 I
b100 c
b100000 A
b100000 P
0"
1,
#320
0,
#325
b1 T
b1 W
b10001 #
b10001 3
b10001 ]
b10110 *
b10110 F
b10110 [
b10110 \
1;
0@
0S
0U
0X
b100000001000 4
b100000001000 Q
1$
b1100001 A
b1100001 P
b1100 &
b1100 ?
b1100 V
b10001 (
b10001 D
b10001 Z
b10001 ^
b0 %
b0 6
b0 O
b0 Y
1,
#330
0,
#335
b1111 T
b0 W
b11110000 (
b11110000 D
b11110000 Z
b11110000 ^
b11110000 #
b11110000 3
b11110000 ]
b10001 *
b10001 F
b10001 [
b10001 \
0;
1@
1S
b1000000001000 4
b1000000001000 Q
1U
1X
b1100000 A
b1100000 P
0$
1,
#340
0,
#345
b1011 5
b1011 H
b1011 K
b1011 f
b0 T
b1011 g
b0 (
b0 D
b0 Z
b0 ^
b0 #
b0 3
b0 ]
b10010 *
b10010 F
b10010 [
b10010 \
b1111 !
b1111 /
b1111 J
b1111 M
b1111 N
b1111 _
b1111 a
b1111 d
b1111 `
0:
1B
b100 7
b100 e
1=
1>
0S
0U
0X
b1011100100000 4
b1011100100000 Q
1$
b1111001 A
b1111001 P
b1111 &
b1111 ?
b1111 V
1,
#350
0,
#355
b1101 T
b1011 g
b11010000 (
b11010000 D
b11010000 Z
b11010000 ^
b11010000 #
b11010000 3
b11010000 ]
b10011 *
b10011 F
b10011 [
b10011 \
b1011 !
b1011 /
b1011 J
b1011 M
b1011 N
b1011 _
b1011 a
b1011 d
1:
0B
b0 7
b0 e
0=
0>
1S
b1000000001000 4
b1000000001000 Q
1U
1X
b1111000 A
b1111000 P
0$
b1011 )
b1011 E
b1011 I
b1011 c
1,
#360
0,
#365
b100 T
b100 W
b1000100 (
b1000100 D
b1000100 Z
b1000100 ^
b1000100 #
b1000100 3
b1000100 ]
b10100 *
b10100 F
b10100 [
b10100 \
1<
0@
0S
0U
0X
b1001 4
b1001 Q
1$
b1101001 A
b1101001 P
b1101 &
b1101 ?
b1101 V
1,
#370
0,
#375
0<
1@
1S
b1000000001000 4
b1000000001000 Q
1U
1X
b1101000 A
b1101000 P
0$
b1011 +
b1011 G
b1011 b
1,
#380
0,
#385
b100 5
b100 H
b100 K
b100 f
b1100 T
b0 W
b100 g
b11000000 #
b11000000 3
b11000000 ]
b10101 *
b10101 F
b10101 [
b10101 \
b100 !
b100 /
b100 J
b100 M
b100 N
b100 _
b100 a
b100 d
18
0:
b10 7
b10 e
1=
1>
0@
0S
0U
0X
b11010000010 4
b11010000010 Q
1$
b100001 A
b100001 P
b100 &
b100 ?
b100 V
b10011000000 (
b10011000000 D
b10011000000 Z
b10011000000 ^
b100 %
b100 6
b100 O
b100 Y
1,
#390
0,
#395
08
1:
b0 7
b0 e
0=
0>
1@
1S
b1000000001000 4
b1000000001000 Q
1U
1X
b100000 A
b100000 P
0$
b100 )
b100 E
b100 I
b100 c
1,
#400
0,
#405
b1 T
b1 W
b10001 #
b10001 3
b10001 ]
b10110 *
b10110 F
b10110 [
b10110 \
1;
0@
0S
0U
0X
b100000001000 4
b100000001000 Q
1$
b1100001 A
b1100001 P
b1100 &
b1100 ?
b1100 V
b10001 (
b10001 D
b10001 Z
b10001 ^
b0 %
b0 6
b0 O
b0 Y
1,
#410
0,
#415
b1111 T
b0 W
b11110000 (
b11110000 D
b11110000 Z
b11110000 ^
b11110000 #
b11110000 3
b11110000 ]
b10001 *
b10001 F
b10001 [
b10001 \
0;
1@
1S
b1000000001000 4
b1000000001000 Q
1U
1X
b1100000 A
b1100000 P
0$
1,
#420
0,
#425
b1011 5
b1011 H
b1011 K
b1011 f
b0 T
b1011 g
b0 (
b0 D
b0 Z
b0 ^
b0 #
b0 3
b0 ]
b10010 *
b10010 F
b10010 [
b10010 \
b1111 !
b1111 /
b1111 J
b1111 M
b1111 N
b1111 _
b1111 a
b1111 d
b1111 `
0:
1B
b100 7
b100 e
1=
1>
0S
0U
0X
b1011100100000 4
b1011100100000 Q
1$
b1111001 A
b1111001 P
b1111 &
b1111 ?
b1111 V
1,
#430
0,
#435
b1101 T
b1011 g
b11010000 (
b11010000 D
b11010000 Z
b11010000 ^
b11010000 #
b11010000 3
b11010000 ]
b10011 *
b10011 F
b10011 [
b10011 \
b1011 !
b1011 /
b1011 J
b1011 M
b1011 N
b1011 _
b1011 a
b1011 d
1:
0B
b0 7
b0 e
0=
0>
1S
b1000000001000 4
b1000000001000 Q
1U
1X
b1111000 A
b1111000 P
0$
b1011 )
b1011 E
b1011 I
b1011 c
1,
#440
0,
